archival/__init__.py
archival/archiver.py
archival/core.py
archival/utils.py
archival_web_spider_netrules-0.0.1.dist-info/LICENSE
archival_web_spider_netrules-0.0.1.dist-info/METADATA
archival_web_spider_netrules-0.0.1.dist-info/WHEEL
archival_web_spider_netrules-0.0.1.dist-info/top_level.txt
archival_web_spider_netrules-0.0.1.dist-info/RECORD
