Metadata-Version: 2.1
Name: archival-web-spider-netrules
Version: 0.0.1
Summary: Using BeautifulSoup and Selenium Webdriver to crawl websites and retrieve their resources to keep documentation for educative purposes.
Home-page: https://github.com/netrules/archival-web-spider
Author: netrules
Author-email: personal@sgonzalez.tech
License: UNKNOWN
Platform: UNKNOWN
Classifier: Programming Language :: Python :: 3
Classifier: License :: CC0 1.0 Universal (CC0 1.0) Public Domain Dedication
Classifier: Operating System :: OS Independent
Requires-Python: >=3.6
